xia_gpt_openai/__init__.py
xia_gpt_openai/gpt.cp311-win_amd64.pyd
xia_gpt_openai-0.1.9.dist-info/LICENSE.txt
xia_gpt_openai-0.1.9.dist-info/METADATA
xia_gpt_openai-0.1.9.dist-info/WHEEL
xia_gpt_openai-0.1.9.dist-info/top_level.txt
xia_gpt_openai-0.1.9.dist-info/RECORD
