Metadata-Version: 2.1
Name: xia-gpt-openai
Version: 0.1.9
Home-page: https://develop.x-i-a.com/docs/xia-gpt-openai/0.1.9/index.html
Author: X-I-A
Author-email: admin@x-i-a.com
Requires-Python: >=3.9
License-File: LICENSE.txt
Requires-Dist: openai
